bootstrap.py
buildout.cfg
notes.txt
setup.py
ore/__init__.py
ore.recipe.svnlib.egg-info/PKG-INFO
ore.recipe.svnlib.egg-info/SOURCES.txt
ore.recipe.svnlib.egg-info/dependency_links.txt
ore.recipe.svnlib.egg-info/entry_points.txt
ore.recipe.svnlib.egg-info/namespace_packages.txt
ore.recipe.svnlib.egg-info/not-zip-safe
ore.recipe.svnlib.egg-info/requires.txt
ore.recipe.svnlib.egg-info/top_level.txt
ore/recipe/__init__.py
ore/recipe/svnlib/README.txt
ore/recipe/svnlib/__init__.py