Metadata-Version: 1.0
Name: ore.recipe.svnlib
Version: 0.1.5
Summary: Buildout recipe for compiling python subversion bindings
Home-page: http://www.python.org/pypi/ore.recipe.svnlib
Author: Kapil Thangavelu
Author-email: kapil.foss@gmail.com
License: ZPL 2.1
Keywords: zope3 subversion svn
Platform: UNKNOWN
Classifier: Programming Language :: Python
Classifier: Framework :: Buildout
Classifier: Intended Audience :: Developers
Classifier: Operating System :: Unix
Classifier: Topic :: Software Development :: Version Control
Classifier: Topic :: System :: Software Distribution
Classifier: License :: OSI Approved :: Zope Public License
